excel_dates/__init__.py
excel_dates/_convert.py
excel_dates/py.typed
excel_dates/version.py
excel_dates-1.0.3.dist-info/LICENSE
excel_dates-1.0.3.dist-info/METADATA
excel_dates-1.0.3.dist-info/WHEEL
excel_dates-1.0.3.dist-info/top_level.txt
excel_dates-1.0.3.dist-info/RECORD
