Metadata-Version: 2.1
Name: excel-dates
Version: 1.0.3
Summary: Convert dates between Excel and Python
Author-email: Bart-Jan Hulsman <hulsmanbj@gmail.com>
Project-URL: repository, https://github.com/AutoActuary/excel-dates
Classifier: Programming Language :: Python :: 3
Classifier: License :: OSI Approved :: MIT License
Classifier: Operating System :: OS Independent
Requires-Python: >=3.7
License-File: LICENSE
